adder/half_adder.vhdl
library ieee;
use ieee.std_logic_1164.all;

entity half_adder is
    port(
        x,y:in std_logic;
        c,s: out std_logic
    );
end half_adder;

architecture rtl of half_adder is  
begin
    c<= x and y;
    s<= x xor y;
end rtl;

adder/full_adder.vhdl
library ieee;
use ieee.std_logic_1164.all;

entity full_adder is
    port(
        x,y,z:in std_logic;
        c,s: out std_logic
    );
end full_adder;

architecture rtl of full_adder is 
component half_adder is
    port(
        x,y:in std_logic;
        c,s: out std_logic
    );
end component; 

signal s1,c1,c2: std_logic;
begin
    half_adder_1: half_adder port map(x,y,c1,s1);
    half_adder_2: half_adder port map(s1,z,c2,s);
    c <= c1 or c2;
end rtl;

adder/tb_full_adder.vhdl
library ieee;
use ieee.std_logic_1164.all;

entity tb_full_adder is
end tb_full_adder;

architecture tb of tb_full_adder is
    component full_adder is
    port(
        x,y,z:in std_logic;
        c,s: out std_logic
    );
end component; 

signal tb_x, tb_y, tb_z : std_logic;
signal tb_c, tb_s : std_logic;

begin
    full_adder_module : full_adder port map(tb_x, tb_y, tb_z, tb_c, tb_s);
    process
    begin
        tb_x <= '0';
        tb_y <= '0';
        tb_z <= '0';
        wait for 10 ns;

        tb_x <= '0';
        tb_y <= '0';
        tb_z <= '1';
        wait for 10 ns;

        tb_x <= '0';
        tb_y <= '1';
        tb_z <= '0';
        wait for 10 ns;

        tb_x <= '0';
        tb_y <= '1';
        tb_z <= '1';
        wait for 10 ns;

        tb_x <= '1';
        tb_y <= '0';
        tb_z <= '0';
        wait for 10 ns;

        tb_x <= '1';
        tb_y <= '0';
        tb_z <= '1';
        wait for 10 ns;

        tb_x <= '1';
        tb_y <= '1';
        tb_z <= '0';
        wait for 10 ns;

        tb_x <= '1';
        tb_y <= '1';
        tb_z <= '1';
        wait for 10 ns;

        wait;
    end process;
end tb;

adder/full_adder_wave.vcd
$date
  Thu Sep 11 14:46:56 2025
$end
$version
  GHDL v0
$end
$timescale
  1 fs
$end
$scope module standard $end
$upscope $end
$scope module std_logic_1164 $end
$upscope $end
$scope module tb_full_adder $end
$var reg 1 ! tb_x $end
$var reg 1 " tb_y $end
$var reg 1 # tb_z $end
$var reg 1 $ tb_c $end
$var reg 1 % tb_s $end
$scope module full_adder_module $end
$var reg 1 & x $end
$var reg 1 ' y $end
$var reg 1 ( z $end
$var reg 1 ) c $end
$var reg 1 * s $end
$var reg 1 + s1 $end
$var reg 1 , c1 $end
$var reg 1 - c2 $end
$scope module half_adder_1 $end
$var reg 1 . x $end
$var reg 1 / y $end
$var reg 1 0 c $end
$var reg 1 1 s $end
$upscope $end
$scope module half_adder_2 $end
$var reg 1 2 x $end
$var reg 1 3 y $end
$var reg 1 4 c $end
$var reg 1 5 s $end
$upscope $end
$upscope $end
$upscope $end
$enddefinitions $end
#0
0!
0"
0#
0$
0%
0&
0'
0(
0)
0*
0+
0,
0-
0.
0/
00
01
02
03
04
05
#10000000
1#
1%
1(
1*
13
15
#20000000
1"
0#
1%
1'
0(
1*
1+
1/
11
12
03
15
#30000000
1#
1$
0%
1(
1)
0*
1-
13
14
05
#40000000
1!
0"
0#
0$
1%
1&
0'
0(
0)
1*
0-
1.
0/
03
04
15
#50000000
1#
1$
0%
1(
1)
0*
1-
13
14
05
#60000000
1"
0#
0%
1'
0(
0*
0+
1,
0-
1/
10
01
02
03
04
05
#70000000
1#
1%
1(
1*
13
15
